Metadata-Version: 1.0
Name: pa27-dataexplorer
Version: 0.1
Summary: A package for quick and easy data exploration and inspection
Home-page: UNKNOWN
Author: UNKNOWN
Author-email: UNKNOWN
License: UNKNOWN
Platform: UNKNOWN
